mirror_tool/__init__.py
mirror_tool/cmd.py
mirror_tool/conf.py
mirror_tool/git_config.py
mirror_tool/git_info.py
mirror_tool/jinja.py
mirror_tool/shared.py
mirror_tool/gitlab/__init__.py
mirror_tool/gitlab/ci_template.py
mirror_tool/gitlab/common.py
mirror_tool/gitlab/promote.py
mirror_tool/gitlab/update.py
mirror_tool-2025.8.dist-info/licenses/LICENSE
mirror_tool-2025.8.dist-info/METADATA
mirror_tool-2025.8.dist-info/WHEEL
mirror_tool-2025.8.dist-info/entry_points.txt
mirror_tool-2025.8.dist-info/top_level.txt
mirror_tool-2025.8.dist-info/RECORD
