Metadata-Version: 2.4
Name: mirror-tool
Version: 2025.8
Summary: A tool for managing git mirrors.
Author-email: Rohan McGovern <rohan@mcgovern.id.au>
License:                     GNU GENERAL PUBLIC LICENSE
Project-URL: Homepage, https://github.com/rohanpm/mirror-tool
Project-URL: Repository, https://github.com/rohanpm/mirror-tool
Requires-Python: >=3.10
License-File: LICENSE
Dynamic: license-file
